LICENSE.md
README.md
pyproject.toml
src/ewoksndreg/__init__.py
src/ewoksndreg/registry.py
src/ewoksndreg.egg-info/PKG-INFO
src/ewoksndreg.egg-info/SOURCES.txt
src/ewoksndreg.egg-info/dependency_links.txt
src/ewoksndreg.egg-info/entry_points.txt
src/ewoksndreg.egg-info/requires.txt
src/ewoksndreg.egg-info/top_level.txt
src/ewoksndreg/dependencies/__init__.py
src/ewoksndreg/dependencies/sitk.py
src/ewoksndreg/evaluation/__init__.py
src/ewoksndreg/evaluation/eval_metrics.py
src/ewoksndreg/evaluation/evaluation.py
src/ewoksndreg/features/__init__.py
src/ewoksndreg/features/registration.py
src/ewoksndreg/features/detection/__init__.py
src/ewoksndreg/features/detection/base.py
src/ewoksndreg/features/detection/scikitimage_backend.py
src/ewoksndreg/features/detection/silx_backend.py
src/ewoksndreg/features/features/__init__.py
src/ewoksndreg/features/features/base.py
src/ewoksndreg/features/features/numpy_backend.py
src/ewoksndreg/features/features/scikitimage_backend.py
src/ewoksndreg/features/features/silx_backend.py
src/ewoksndreg/features/mapping/__init__.py
src/ewoksndreg/features/mapping/base.py
src/ewoksndreg/features/mapping/lstsq.py
src/ewoksndreg/features/mapping/numpy_backend.py
src/ewoksndreg/features/mapping/scikitimage_backend.py
src/ewoksndreg/features/mapping/scipy_backend.py
src/ewoksndreg/features/matching/__init__.py
src/ewoksndreg/features/matching/base.py
src/ewoksndreg/features/matching/numpy_backend.py
src/ewoksndreg/features/matching/scikitimage_backend.py
src/ewoksndreg/features/matching/silx_backend.py
src/ewoksndreg/gui/stack_selector.py
src/ewoksndreg/intensities/__init__.py
src/ewoksndreg/intensities/base.py
src/ewoksndreg/intensities/kornia_backend.py
src/ewoksndreg/intensities/metrics.py
src/ewoksndreg/intensities/numpy_backend.py
src/ewoksndreg/intensities/registration.py
src/ewoksndreg/intensities/scikitimage_backend.py
src/ewoksndreg/intensities/simpleitk_backend.py
src/ewoksndreg/intensities/torch_metrics.py
src/ewoksndreg/intensities/types.py
src/ewoksndreg/io/__init__.py
src/ewoksndreg/io/data_for_registration.py
src/ewoksndreg/io/input_stack.py
src/ewoksndreg/io/nexus.py
src/ewoksndreg/io/output_stack.py
src/ewoksndreg/math/__init__.py
