Metadata-Version: 2.4
Name: ewoksndreg
Version: 0.4.0
Summary: Workflows for data registration (e.g. curve, image and volume registration).
Author-email: ESRF <dau-pydev@esrf.fr>
License: # MIT License
Project-URL: Homepage, https://gitlab.esrf.fr/workflow/ewoksapps/ewoksndreg
Project-URL: Documentation, https://ewoksndreg.readthedocs.io/
Project-URL: Repository, https://gitlab.esrf.fr/workflow/ewoksapps/ewoksndreg
Project-URL: Issues, https://gitlab.esrf.fr/workflow/ewoksapps/ewoksndreg/issues
Project-URL: Changelog, https://gitlab.esrf.fr/workflow/ewoksapps/ewoksndreg/-/blob/main/CHANGELOG.md
Keywords: orange3 add-on,ewoks
Classifier: Intended Audience :: Science/Research
Classifier: License :: OSI Approved :: MIT License
Classifier: Programming Language :: Python :: 3
Requires-Python: >=3.8
License-File: LICENSE.md
Requires-Dist: numpy>=1.15
Requires-Dist: silx>=1.1.2
Requires-Dist: pyopencl
Requires-Dist: ewokscore>=1.4.0
Requires-Dist: ewoksorange>=0.1.2
Requires-Dist: ewoksdata>=0.1
Requires-Dist: packaging
Requires-Dist: scipy>=1.5.4
Requires-Dist: scikit-image>=0.19
Provides-Extra: all
Requires-Dist: kornia>=0.7.0; extra == "all"
Requires-Dist: simpleitk>=2.2.1; extra == "all"
Provides-Extra: full
Requires-Dist: ewoksndreg[all]; extra == "full"
Requires-Dist: pyqt6; extra == "full"
Provides-Extra: test
Requires-Dist: pytest>=7; extra == "test"
Requires-Dist: pyqt6; extra == "test"
Requires-Dist: importlib-resources; python_version <= "3.9" and extra == "test"
Provides-Extra: dev
Requires-Dist: ewoksndreg[test]; extra == "dev"
Requires-Dist: black>=25; extra == "dev"
Requires-Dist: flake8>=4; extra == "dev"
Provides-Extra: doc
Requires-Dist: ewoksndreg[test]; extra == "doc"
Requires-Dist: ewoksndreg[full]; extra == "doc"
Requires-Dist: sphinx>=4.5; extra == "doc"
Requires-Dist: sphinx-autodoc-typehints>=1.16; extra == "doc"
Requires-Dist: pydata-sphinx-theme>=0.14.4; extra == "doc"
Requires-Dist: ewokssphinx; extra == "doc"
Dynamic: license-file
